shapeObject/MergeCommonShapes.py
shapeObject/ShapeObject.py
shapeObject/__init__.py
shapeObject/supports.py
shapeObject/write_shapefile.py
shapeObject-0.5.2.dist-info/LICENSE
shapeObject-0.5.2.dist-info/METADATA
shapeObject-0.5.2.dist-info/WHEEL
shapeObject-0.5.2.dist-info/top_level.txt
shapeObject-0.5.2.dist-info/RECORD
